cvo251102app/__init__.py
cvo251102app/__main__.py
cvo251102app/cvo251102app.py
cvo251102app/py.typed
cvo251102app-0.6.0.dist-info/WHEEL
cvo251102app-0.6.0.dist-info/entry_points.txt
cvo251102app-0.6.0.dist-info/METADATA
cvo251102app-0.6.0.dist-info/RECORD
