Metadata-Version: 2.3
Name: cvo251102app
Version: 0.6.0
Summary: Development flow as Paleofuturistic Python
Author: Paleofuturistic Python
Author-email: Paleofuturistic Python <me@here.now>
Classifier: License :: OSI Approved :: Apache Software License
Classifier: Programming Language :: Python :: 3.12
Requires-Dist: cvo251102lib>=0.1.0
Requires-Python: >=3.12
